CHANGES.rst
MANIFEST.in
README.rst
setup.cfg
setup.py
src/spirit/__init__.py
src/spirit.zptlint.egg-info/PKG-INFO
src/spirit.zptlint.egg-info/SOURCES.txt
src/spirit.zptlint.egg-info/dependency_links.txt
src/spirit.zptlint.egg-info/entry_points.txt
src/spirit.zptlint.egg-info/namespace_packages.txt
src/spirit.zptlint.egg-info/not-zip-safe
src/spirit.zptlint.egg-info/requires.txt
src/spirit.zptlint.egg-info/top_level.txt
src/spirit/zptlint/__init__.py