Metadata-Version: 1.1
Name: spirit.zptlint
Version: 0.1
Summary: Linter for Zope Page Templates.
Home-page: https://github.com/it-spirit/spirit.zptlint
Author: it-spirit
Author-email: development@it-spir.it
License: BSD
Download-URL: http://pypi.python.org/pypi/spirit.zptlint
Keywords: zope,linter,template
Platform: UNKNOWN
Classifier: Development Status :: 5 - Production/Stable
Classifier: Environment :: Console
Classifier: Intended Audience :: Developers
Classifier: License :: OSI Approved :: BSD License
Classifier: Natural Language :: English
Classifier: Operating System :: OS Independent
Classifier: Programming Language :: Python
Classifier: Programming Language :: Python :: 2.7
Classifier: Topic :: Software Development :: Code Generators
Classifier: Topic :: Utilities
